examples/__init__.py
examples/async_example.py
examples/raw_example.py
examples/sync_example.py
spamprotection/__init__.py
spamprotection/client.py
spamprotection/errors.py
spamprotection/sync.py
spamprotection/types.py
spamprotection/utils.py
Intellivoid_SPB-0.1.1.dist-info/LICENSE
Intellivoid_SPB-0.1.1.dist-info/METADATA
Intellivoid_SPB-0.1.1.dist-info/WHEEL
Intellivoid_SPB-0.1.1.dist-info/top_level.txt
Intellivoid_SPB-0.1.1.dist-info/RECORD
